Metadata-Version: 2.1
Name: jsonmorph
Version: 0.0.5
Summary: Tool for transforming a JSON to another JSON by defining a configuration JSON setting file.
Home-page: UNKNOWN
Author: Bidut Karki
Author-email: bidutjava3@gmail.com
License: UNKNOWN
Platform: UNKNOWN
